askyourdocs/__init__.py
askyourdocs/core/__init__.py
askyourdocs/core/config.py
askyourdocs/core/ingestion.py
askyourdocs/core/retrieval.py
askyourdocs/core/storage.py
askyourdocs/document_loaders/__init__.py
askyourdocs/document_loaders/code.py
askyourdocs/document_loaders/office.py
askyourdocs/document_loaders/pdf.py
askyourdocs/document_loaders/text.py
askyourdocs/main.py
askyourdocs/utils/__init__.py
askyourdocs/utils/logging.py
askyourdocs/utils/validation.py
askyourdocs-1.0.0.dist-info/LICENSE
askyourdocs-1.0.0.dist-info/METADATA
askyourdocs-1.0.0.dist-info/WHEEL
askyourdocs-1.0.0.dist-info/entry_points.txt
askyourdocs-1.0.0.dist-info/RECORD
