Metadata-Version: 2.3
Name: askyourdocs
Version: 1.0.0
Summary: Privacy-first, local-only CLI tool that transforms document collections into an intelligent Q&A system
License: MIT
Keywords: rag,ai,llm,documents,question-answering,search,privacy,local,cli,llamaindex
Author: Lincoln Simba
Author-email: lincolncmba@gmail.com
Requires-Python: >=3.10,<3.14
Classifier: Development Status :: 5 - Production/Stable
Classifier: Intended Audience :: Developers
Classifier: Intended Audience :: End Users/Desktop
Classifier: Intended Audience :: Science/Research
Classifier: License :: OSI Approved :: MIT License
Classifier: Operating System :: OS Independent
Classifier: Programming Language :: Python :: 3
Classifier: Programming Language :: Python :: 3.10
Classifier: Programming Language :: Python :: 3.11
Classifier: Programming Language :: Python :: 3.12
Classifier: Programming Language :: Python :: 3.13
Classifier: Topic :: Office/Business :: Office Suites
Classifier: Topic :: Scientific/Engineering :: Artificial Intelligence
Classifier: Topic :: Text Processing :: Indexing
Provides-Extra: all
Provides-Extra: dev
Provides-Extra: docs
Provides-Extra: gpu
Requires-Dist: anthropic (==0.66.0)
Requires-Dist: beautifulsoup4 (==4.13.5)
Requires-Dist: chromadb (==1.0.20)
Requires-Dist: click (==8.2.1)
Requires-Dist: llama-index (==0.13.3)
Requires-Dist: llama-index-core (==0.13.3)
Requires-Dist: llama-index-embeddings-huggingface (==0.6.0)
Requires-Dist: llama-index-embeddings-openai (==0.5.0)
Requires-Dist: llama-index-llms-anthropic (==0.8.6)
Requires-Dist: llama-index-llms-azure-openai (==0.4.1)
Requires-Dist: llama-index-llms-ollama (==0.7.1)
Requires-Dist: llama-index-llms-openai (==0.5.4)
Requires-Dist: llama-index-vector-stores-chroma (==0.5.2)
Requires-Dist: lxml (==5.3.0)
Requires-Dist: markdown (==3.7)
Requires-Dist: openai (==1.102.0)
Requires-Dist: pydantic (==2.11.7)
Requires-Dist: pypdf (==6.0.0)
Requires-Dist: python-docx (==1.1.2)
Requires-Dist: python-pptx (==0.6.23)
Requires-Dist: pyyaml (==6.0.2)
Requires-Dist: requests (==2.32.5)
Requires-Dist: rich (==14.1.0)
Requires-Dist: sentence-transformers (==5.1.0)
Requires-Dist: torch (==2.8.0) ; extra == "gpu"
Requires-Dist: tqdm (==4.67.1)
Requires-Dist: transformers (==4.56.0) ; extra == "gpu"
Requires-Dist: watchdog (==6.0.0)
Project-URL: Documentation, https://github.com/lincmba/askyourdocs/blob/main/README.md
Project-URL: Homepage, https://github.com/lincmba/askyourdocs
Project-URL: Repository, https://github.com/lincmba/askyourdocs
